emitter/__init__.py
socket.io_emitter_2-0.1.5.dist-info/DESCRIPTION.rst
socket.io_emitter_2-0.1.5.dist-info/METADATA
socket.io_emitter_2-0.1.5.dist-info/RECORD
socket.io_emitter_2-0.1.5.dist-info/WHEEL
socket.io_emitter_2-0.1.5.dist-info/metadata.json
socket.io_emitter_2-0.1.5.dist-info/top_level.txt
