Metadata-Version: 2.0
Name: socket.io-emitter-2
Version: 0.1.5
Summary: A Python implementation of socket.io-emitter
Home-page: https://github.com/ziyasal/socket.io-python-emitter
Author: Ziya SARIKAYA
Author-email: sarikayaziya@gmail.com
License: LICENSE
Platform: UNKNOWN
Requires-Dist: msgpack-python
Requires-Dist: redis
